redisevents/__init__.py
redisevents/redisevents.py
redisevents-0.0.1.dist-info/LICENSE
redisevents-0.0.1.dist-info/METADATA
redisevents-0.0.1.dist-info/WHEEL
redisevents-0.0.1.dist-info/top_level.txt
redisevents-0.0.1.dist-info/RECORD
